mhcgnomes/__init__.py
mhcgnomes/allele.py
mhcgnomes/allele_annotations.py
mhcgnomes/allele_without_gene.py
mhcgnomes/class2_locus.py
mhcgnomes/class2_pair.py
mhcgnomes/common.py
mhcgnomes/data.py
mhcgnomes/dataframe.py
mhcgnomes/errors.py
mhcgnomes/function_api.py
mhcgnomes/gene.py
mhcgnomes/haplotype.py
mhcgnomes/mhc_class.py
mhcgnomes/mhc_class_helpers.py
mhcgnomes/mutation.py
mhcgnomes/normalizing_dictionary.py
mhcgnomes/normalizing_set.py
mhcgnomes/pair.py
mhcgnomes/parser.py
mhcgnomes/parsing_helpers.py
mhcgnomes/result.py
mhcgnomes/result_sorting.py
mhcgnomes/result_with_gene.py
mhcgnomes/result_with_mhc_class.py
mhcgnomes/result_with_multiple_alleles.py
mhcgnomes/result_with_species.py
mhcgnomes/serotype.py
mhcgnomes/species.py
mhcgnomes/standard_format.py
mhcgnomes/token.py
mhcgnomes/token_canonical_sequences.py
mhcgnomes/token_substitution.py
mhcgnomes/tokenize.py
mhcgnomes/version.py
mhcgnomes/data/allele_aliases.yaml
mhcgnomes/data/class2_locus_aliases.yaml
mhcgnomes/data/common_genes.yaml
mhcgnomes/data/curated_allele_aliases.yaml
mhcgnomes/data/default_alleles.yaml
mhcgnomes/data/gene_aliases.yaml
mhcgnomes/data/haplotypes.yaml
mhcgnomes/data/known_alleles.yaml
mhcgnomes/data/serotypes.yaml
mhcgnomes/data/species.yaml
mhcgnomes-1.8.6.dist-info/LICENSE
mhcgnomes-1.8.6.dist-info/METADATA
mhcgnomes-1.8.6.dist-info/WHEEL
mhcgnomes-1.8.6.dist-info/top_level.txt
mhcgnomes-1.8.6.dist-info/RECORD
