Metadata-Version: 2.1
Name: mhcgnomes
Version: 1.8.6
Summary: Python library for parsing MHC nomenclature in the wild
Home-page: https://github.com/til-unc/mhcgnomes
Author: Alex Rubinsteyn
Author-email: alex.rubinsteyn@unc.edu
License: http://www.apache.org/licenses/LICENSE-2.0.html
Classifier: Development Status :: 4 - Beta
Classifier: Environment :: Console
Classifier: Operating System :: OS Independent
Classifier: Intended Audience :: Science/Research
Classifier: License :: OSI Approved :: Apache Software License
Classifier: Programming Language :: Python
Classifier: Topic :: Scientific/Engineering :: Bio-Informatics
License-File: LICENSE
Requires-Dist: serializable
Requires-Dist: PyYAML (>=5.4)
Requires-Dist: pandas
Requires-Dist: numpy
